{
  "finishedAt": "2026-04-21T18:15:36.766Z",
  "execute": false,
  "userId": 1,
  "shopDomain": "ivanreseller-2.myshopify.com",
  "reconciledListings": 33,
  "breakdown": {
    "ACTIVE_AND_STOREFRONT_OK": 25,
    "ACTIVE_BUT_STOREFRONT_LINK_BROKEN": 0,
    "ACTIVE_BUT_HANDLE_MISMATCH": 0,
    "DRAFT": 8,
    "FAILED": 0,
    "ORPHANED / INCONSISTENT": 0
  },
  "repairedHandleMismatches": 0,
  "repairedBrokenActiveStatuses": 0,
  "rows": [
    {
      "listingId": 1,
      "productTitle": "Earbuds wireless bluetooth headset",
      "cjProductId": "95114A85-CB4B-49B8-ACBC-0CDFA082E2B5",
      "localStatusBefore": "ACTIVE",
      "classification": "ACTIVE_AND_STOREFRONT_OK",
      "shopifyProductId": "gid://shopify/Product/9145455837396",
      "shopifyVariantId": "gid://shopify/ProductVariant/47821954646228",
      "storedShopifyHandle": "earbuds-wireless-bluetooth-headset-cjxfbxej02656-white",
      "adminShopifyHandle": "earbuds-wireless-bluetooth-headset-cjxfbxej02656-white",
      "adminShopifyStatus": "ACTIVE",
      "generatedStorefrontUrl": "https://ivanreseller-2.myshopify.com/products/earbuds-wireless-bluetooth-headset-cjxfbxej02656-white",
      "storefront": {
        "status": 200,
        "finalUrl": "https://ivanreseller-2.myshopify.com/products/earbuds-wireless-bluetooth-headset-cjxfbxej02656-white",
        "buyerFacingOk": true,
        "passwordGate": false,
        "hasAddToCart": true,
        "hasPrice": true
      },
      "notes": []
    },
    {
      "listingId": 2,
      "productTitle": "Wireless TWS Stereo Earbuds",
      "cjProductId": "1999395299549302785",
      "localStatusBefore": "ACTIVE",
      "classification": "ACTIVE_AND_STOREFRONT_OK",
      "shopifyProductId": "gid://shopify/Product/9145457803476",
      "shopifyVariantId": "gid://shopify/ProductVariant/47821968474324",
      "storedShopifyHandle": "wireless-tws-stereo-earbuds-cjej264155501az",
      "adminShopifyHandle": "wireless-tws-stereo-earbuds-cjej264155501az",
      "adminShopifyStatus": "ACTIVE",
      "generatedStorefrontUrl": "https://ivanreseller-2.myshopify.com/products/wireless-tws-stereo-earbuds-cjej264155501az",
      "storefront": {
        "status": 200,
        "finalUrl": "https://ivanreseller-2.myshopify.com/products/wireless-tws-stereo-earbuds-cjej264155501az",
        "buyerFacingOk": true,
        "passwordGate": false,
        "hasAddToCart": true,
        "hasPrice": true
      },
      "notes": []
    },
    {
      "listingId": 3,
      "productTitle": "Neck Pillow Travel Pillow",
      "cjProductId": "479E2C57-73CA-4F63-B77E-6ABC5B2F32D5",
      "localStatusBefore": "ACTIVE",
      "classification": "ACTIVE_AND_STOREFRONT_OK",
      "shopifyProductId": "gid://shopify/Product/9145755435220",
      "shopifyVariantId": "gid://shopify/ProductVariant/47823252390100",
      "storedShopifyHandle": "neck-pillow-travel-pillow-cjjjjfzt00492-pink",
      "adminShopifyHandle": "neck-pillow-travel-pillow-cjjjjfzt00492-pink",
      "adminShopifyStatus": "ACTIVE",
      "generatedStorefrontUrl": "https://ivanreseller-2.myshopify.com/products/neck-pillow-travel-pillow-cjjjjfzt00492-pink",
      "storefront": {
        "status": 200,
        "finalUrl": "https://ivanreseller-2.myshopify.com/products/neck-pillow-travel-pillow-cjjjjfzt00492-pink",
        "buyerFacingOk": true,
        "passwordGate": false,
        "hasAddToCart": true,
        "hasPrice": true
      },
      "notes": []
    },
    {
      "listingId": 4,
      "productTitle": "PD 20W Universal Travel Adapter Plug",
      "cjProductId": "2602050314241608000",
      "localStatusBefore": "ACTIVE",
      "classification": "ACTIVE_AND_STOREFRONT_OK",
      "shopifyProductId": "gid://shopify/Product/9146322550996",
      "shopifyVariantId": "gid://shopify/ProductVariant/47825245372628",
      "storedShopifyHandle": "pd-20w-universal-travel-adapter-plug-cjyd275457305ev",
      "adminShopifyHandle": "pd-20w-universal-travel-adapter-plug-cjyd275457305ev",
      "adminShopifyStatus": "ACTIVE",
      "generatedStorefrontUrl": "https://ivanreseller-2.myshopify.com/products/pd-20w-universal-travel-adapter-plug-cjyd275457305ev",
      "storefront": {
        "status": 200,
        "finalUrl": "https://ivanreseller-2.myshopify.com/products/pd-20w-universal-travel-adapter-plug-cjyd275457305ev",
        "buyerFacingOk": true,
        "passwordGate": false,
        "hasAddToCart": true,
        "hasPrice": true
      },
      "notes": []
    },
    {
      "listingId": 5,
      "productTitle": "9Pcs Clothes Storage Bags Water-Resistant Travel Luggage Organizer Clothing Packing Cubes",
      "cjProductId": "1990664736726372353",
      "localStatusBefore": "ACTIVE",
      "classification": "ACTIVE_AND_STOREFRONT_OK",
      "shopifyProductId": "gid://shopify/Product/9146322780372",
      "shopifyVariantId": "gid://shopify/ProductVariant/47825261494484",
      "storedShopifyHandle": "9pcs-clothes-storage-bags-water-resistant-travel-luggage-organizer-clothing-packing-cubes",
      "adminShopifyHandle": "9pcs-clothes-storage-bags-water-resistant-travel-luggage-organizer-clothing-packing-cubes",
      "adminShopifyStatus": "ACTIVE",
      "generatedStorefrontUrl": "https://ivanreseller-2.myshopify.com/products/9pcs-clothes-storage-bags-water-resistant-travel-luggage-organizer-clothing-packing-cubes",
      "storefront": {
        "status": 200,
        "finalUrl": "https://ivanreseller-2.myshopify.com/products/9pcs-clothes-storage-bags-water-resistant-travel-luggage-organizer-clothing-packing-cubes",
        "buyerFacingOk": true,
        "passwordGate": false,
        "hasAddToCart": true,
        "hasPrice": true
      },
      "notes": []
    },
    {
      "listingId": 6,
      "productTitle": "U Shaped Pillow Travel Neck Pillow Memory Foam",
      "cjProductId": "1645725464138358784",
      "localStatusBefore": "ACTIVE",
      "classification": "ACTIVE_AND_STOREFRONT_OK",
      "shopifyProductId": "gid://shopify/Product/9146322976980",
      "shopifyVariantId": "gid://shopify/ProductVariant/47825274831060",
      "storedShopifyHandle": "u-shaped-pillow-travel-neck-pillow-memory-foam-cjjt173163301az",
      "adminShopifyHandle": "u-shaped-pillow-travel-neck-pillow-memory-foam-cjjt173163301az",
      "adminShopifyStatus": "ACTIVE",
      "generatedStorefrontUrl": "https://ivanreseller-2.myshopify.com/products/u-shaped-pillow-travel-neck-pillow-memory-foam-cjjt173163301az",
      "storefront": {
        "status": 200,
        "finalUrl": "https://ivanreseller-2.myshopify.com/products/u-shaped-pillow-travel-neck-pillow-memory-foam-cjjt173163301az",
        "buyerFacingOk": true,
        "passwordGate": false,
        "hasAddToCart": true,
        "hasPrice": true
      },
      "notes": []
    },
    {
      "listingId": 7,
      "productTitle": "Bottled travel cosmetics silicone bottle storage bottle",
      "cjProductId": "A863730C-A987-4543-B348-3AEAA3A7043E",
      "localStatusBefore": "ACTIVE",
      "classification": "ACTIVE_AND_STOREFRONT_OK",
      "shopifyProductId": "gid://shopify/Product/9146323173588",
      "shopifyVariantId": "gid://shopify/ProductVariant/47825287741652",
      "storedShopifyHandle": "bottled-travel-cosmetics-silicone-bottle-storage-bottle-cjjjjtcc00174-blue",
      "adminShopifyHandle": "bottled-travel-cosmetics-silicone-bottle-storage-bottle-cjjjjtcc00174-blue",
      "adminShopifyStatus": "ACTIVE",
      "generatedStorefrontUrl": "https://ivanreseller-2.myshopify.com/products/bottled-travel-cosmetics-silicone-bottle-storage-bottle-cjjjjtcc00174-blue",
      "storefront": {
        "status": 200,
        "finalUrl": "https://ivanreseller-2.myshopify.com/products/bottled-travel-cosmetics-silicone-bottle-storage-bottle-cjjjjtcc00174-blue",
        "buyerFacingOk": true,
        "passwordGate": false,
        "hasAddToCart": true,
        "hasPrice": true
      },
      "notes": []
    },
    {
      "listingId": 8,
      "productTitle": "Luggage Scale Portable Electronic Scale",
      "cjProductId": "1429375206241210368",
      "localStatusBefore": "ACTIVE",
      "classification": "ACTIVE_AND_STOREFRONT_OK",
      "shopifyProductId": "gid://shopify/Product/9146323271892",
      "shopifyVariantId": "gid://shopify/ProductVariant/47825294196948",
      "storedShopifyHandle": "luggage-scale-portable-electronic-scale-cjjt126011601az",
      "adminShopifyHandle": "luggage-scale-portable-electronic-scale-cjjt126011601az",
      "adminShopifyStatus": "ACTIVE",
      "generatedStorefrontUrl": "https://ivanreseller-2.myshopify.com/products/luggage-scale-portable-electronic-scale-cjjt126011601az",
      "storefront": {
        "status": 200,
        "finalUrl": "https://ivanreseller-2.myshopify.com/products/luggage-scale-portable-electronic-scale-cjjt126011601az",
        "buyerFacingOk": true,
        "passwordGate": false,
        "hasAddToCart": true,
        "hasPrice": true
      },
      "notes": []
    },
    {
      "listingId": 9,
      "productTitle": "USB C multi hub docking station",
      "cjProductId": "A8E4C408-6970-42DE-86C7-C5629D6AD36C",
      "localStatusBefore": "ACTIVE",
      "classification": "ACTIVE_AND_STOREFRONT_OK",
      "shopifyProductId": "gid://shopify/Product/9146323402964",
      "shopifyVariantId": "gid://shopify/ProductVariant/47825303863508",
      "storedShopifyHandle": "usb-c-multi-hub-docking-station-cjxflpyp00087-m9vc01",
      "adminShopifyHandle": "usb-c-multi-hub-docking-station-cjxflpyp00087-m9vc01",
      "adminShopifyStatus": "ACTIVE",
      "generatedStorefrontUrl": "https://ivanreseller-2.myshopify.com/products/usb-c-multi-hub-docking-station-cjxflpyp00087-m9vc01",
      "storefront": {
        "status": 200,
        "finalUrl": "https://ivanreseller-2.myshopify.com/products/usb-c-multi-hub-docking-station-cjxflpyp00087-m9vc01",
        "buyerFacingOk": true,
        "passwordGate": false,
        "hasAddToCart": true,
        "hasPrice": true
      },
      "notes": []
    },
    {
      "listingId": 10,
      "productTitle": "Simple Vertical Aluminum Laptop Stand Adjustable",
      "cjProductId": "1631221139164901376",
      "localStatusBefore": "ACTIVE",
      "classification": "ACTIVE_AND_STOREFRONT_OK",
      "shopifyProductId": "gid://shopify/Product/9146323435732",
      "shopifyVariantId": "gid://shopify/ProductVariant/47825303896276",
      "storedShopifyHandle": "simple-vertical-aluminum-laptop-stand-adjustable-cjjt169656604dw",
      "adminShopifyHandle": "simple-vertical-aluminum-laptop-stand-adjustable-cjjt169656604dw",
      "adminShopifyStatus": "ACTIVE",
      "generatedStorefrontUrl": "https://ivanreseller-2.myshopify.com/products/simple-vertical-aluminum-laptop-stand-adjustable-cjjt169656604dw",
      "storefront": {
        "status": 200,
        "finalUrl": "https://ivanreseller-2.myshopify.com/products/simple-vertical-aluminum-laptop-stand-adjustable-cjjt169656604dw",
        "buyerFacingOk": true,
        "passwordGate": false,
        "hasAddToCart": true,
        "hasPrice": true
      },
      "notes": []
    },
    {
      "listingId": 11,
      "productTitle": "Dust-proof Storage Cable Management Box Hub Organizer Box",
      "cjProductId": "1414780039492407296",
      "localStatusBefore": "ACTIVE",
      "classification": "ACTIVE_AND_STOREFRONT_OK",
      "shopifyProductId": "gid://shopify/Product/9146323501268",
      "shopifyVariantId": "gid://shopify/ProductVariant/47825304027348",
      "storedShopifyHandle": "dust-proof-storage-cable-management-box-hub-organizer-box-cjcc121180401az",
      "adminShopifyHandle": "dust-proof-storage-cable-management-box-hub-organizer-box-cjcc121180401az",
      "adminShopifyStatus": "ACTIVE",
      "generatedStorefrontUrl": "https://ivanreseller-2.myshopify.com/products/dust-proof-storage-cable-management-box-hub-organizer-box-cjcc121180401az",
      "storefront": {
        "status": 200,
        "finalUrl": "https://ivanreseller-2.myshopify.com/products/dust-proof-storage-cable-management-box-hub-organizer-box-cjcc121180401az",
        "buyerFacingOk": true,
        "passwordGate": false,
        "hasAddToCart": true,
        "hasPrice": true
      },
      "notes": []
    },
    {
      "listingId": 12,
      "productTitle": "Anti-Fatigue Rubber Floor Mat Dome Hollow Anti-static",
      "cjProductId": "2509160959231628300",
      "localStatusBefore": "ACTIVE",
      "classification": "ACTIVE_AND_STOREFRONT_OK",
      "shopifyProductId": "gid://shopify/Product/9146323534036",
      "shopifyVariantId": "gid://shopify/ProductVariant/47825304060116",
      "storedShopifyHandle": "anti-fatigue-rubber-floor-mat-dome-hollow-anti-static-cjyd253208001az",
      "adminShopifyHandle": "anti-fatigue-rubber-floor-mat-dome-hollow-anti-static-cjyd253208001az",
      "adminShopifyStatus": "ACTIVE",
      "generatedStorefrontUrl": "https://ivanreseller-2.myshopify.com/products/anti-fatigue-rubber-floor-mat-dome-hollow-anti-static-cjyd253208001az",
      "storefront": {
        "status": 200,
        "finalUrl": "https://ivanreseller-2.myshopify.com/products/anti-fatigue-rubber-floor-mat-dome-hollow-anti-static-cjyd253208001az",
        "buyerFacingOk": true,
        "passwordGate": false,
        "hasAddToCart": true,
        "hasPrice": true
      },
      "notes": []
    },
    {
      "listingId": 13,
      "productTitle": "Magnetic Phone Holder For Car, Dashboard Car Phone Holder Mount Magnetic Stainless Steel Car Phone Holder - Dashboard Mount, Water-resistant, Rotatable",
      "cjProductId": "1809888855471312896",
      "localStatusBefore": "ACTIVE",
      "classification": "ACTIVE_AND_STOREFRONT_OK",
      "shopifyProductId": "gid://shopify/Product/9146323599572",
      "shopifyVariantId": "gid://shopify/ProductVariant/47825304223956",
      "storedShopifyHandle": "magnetic-phone-holder-for-car-dashboard-car-phone-holder-mount-magnetic-stainless-steel-ca",
      "adminShopifyHandle": "magnetic-phone-holder-for-car-dashboard-car-phone-holder-mount-magnetic-stainless-steel-ca",
      "adminShopifyStatus": "ACTIVE",
      "generatedStorefrontUrl": "https://ivanreseller-2.myshopify.com/products/magnetic-phone-holder-for-car-dashboard-car-phone-holder-mount-magnetic-stainless-steel-ca",
      "storefront": {
        "status": 200,
        "finalUrl": "https://ivanreseller-2.myshopify.com/products/magnetic-phone-holder-for-car-dashboard-car-phone-holder-mount-magnetic-stainless-steel-ca",
        "buyerFacingOk": true,
        "passwordGate": false,
        "hasAddToCart": true,
        "hasPrice": true
      },
      "notes": []
    },
    {
      "listingId": 14,
      "productTitle": "Portable Phone Holder Stand Desk Tablet With Mirror Mobile Phone Bracket With Mirror Foldable Phone Holder",
      "cjProductId": "1426120141564940288",
      "localStatusBefore": "ACTIVE",
      "classification": "ACTIVE_AND_STOREFRONT_OK",
      "shopifyProductId": "gid://shopify/Product/9146323632340",
      "shopifyVariantId": "gid://shopify/ProductVariant/47825304256724",
      "storedShopifyHandle": "portable-phone-holder-stand-desk-tablet-with-mirror-mobile-phone-bracket-with-mirror-folda",
      "adminShopifyHandle": "portable-phone-holder-stand-desk-tablet-with-mirror-mobile-phone-bracket-with-mirror-folda",
      "adminShopifyStatus": "ACTIVE",
      "generatedStorefrontUrl": "https://ivanreseller-2.myshopify.com/products/portable-phone-holder-stand-desk-tablet-with-mirror-mobile-phone-bracket-with-mirror-folda",
      "storefront": {
        "status": 200,
        "finalUrl": "https://ivanreseller-2.myshopify.com/products/portable-phone-holder-stand-desk-tablet-with-mirror-mobile-phone-bracket-with-mirror-folda",
        "buyerFacingOk": true,
        "passwordGate": false,
        "hasAddToCart": true,
        "hasPrice": true
      },
      "notes": []
    },
    {
      "listingId": 15,
      "productTitle": "bluetooth tracker key finder",
      "cjProductId": "A6235D6D-EC07-4570-8057-E5A8773EF877",
      "localStatusBefore": "ACTIVE",
      "classification": "ACTIVE_AND_STOREFRONT_OK",
      "shopifyProductId": "gid://shopify/Product/9146323665108",
      "shopifyVariantId": "gid://shopify/ProductVariant/47825304289492",
      "storedShopifyHandle": "bluetooth-tracker-key-finder-cjjsaqjb00013-champagne",
      "adminShopifyHandle": "bluetooth-tracker-key-finder-cjjsaqjb00013-champagne",
      "adminShopifyStatus": "ACTIVE",
      "generatedStorefrontUrl": "https://ivanreseller-2.myshopify.com/products/bluetooth-tracker-key-finder-cjjsaqjb00013-champagne",
      "storefront": {
        "status": 200,
        "finalUrl": "https://ivanreseller-2.myshopify.com/products/bluetooth-tracker-key-finder-cjjsaqjb00013-champagne",
        "buyerFacingOk": true,
        "passwordGate": false,
        "hasAddToCart": true,
        "hasPrice": true
      },
      "notes": []
    },
    {
      "listingId": 16,
      "productTitle": "Portable Mini Large  Ccity 10000mAh Power Bank",
      "cjProductId": "CD9753E5-1CF4-4C44-AEBD-098F42A87EB7",
      "localStatusBefore": "ACTIVE",
      "classification": "ACTIVE_AND_STOREFRONT_OK",
      "shopifyProductId": "gid://shopify/Product/9146323697876",
      "shopifyVariantId": "gid://shopify/ProductVariant/47825304322260",
      "storedShopifyHandle": "portable-mini-large-ccity-10000mah-power-bank-cjsjsjcd00363-white-10000mah",
      "adminShopifyHandle": "portable-mini-large-ccity-10000mah-power-bank-cjsjsjcd00363-white-10000mah",
      "adminShopifyStatus": "ACTIVE",
      "generatedStorefrontUrl": "https://ivanreseller-2.myshopify.com/products/portable-mini-large-ccity-10000mah-power-bank-cjsjsjcd00363-white-10000mah",
      "storefront": {
        "status": 200,
        "finalUrl": "https://ivanreseller-2.myshopify.com/products/portable-mini-large-ccity-10000mah-power-bank-cjsjsjcd00363-white-10000mah",
        "buyerFacingOk": true,
        "passwordGate": false,
        "hasAddToCart": true,
        "hasPrice": true
      },
      "notes": []
    },
    {
      "listingId": 17,
      "productTitle": "2 In 1 Phone Computer Screen Cleaner Kit For Screen Dust Removal Microfiber Cloth Set",
      "cjProductId": "28191F94-A25B-4A64-A57B-E4674E560FAD",
      "localStatusBefore": "ACTIVE",
      "classification": "ACTIVE_AND_STOREFRONT_OK",
      "shopifyProductId": "gid://shopify/Product/9146323763412",
      "shopifyVariantId": "gid://shopify/ProductVariant/47825304387796",
      "storedShopifyHandle": "2-in-1-phone-computer-screen-cleaner-kit-for-screen-dust-removal-microfiber-cloth-set-cjsj",
      "adminShopifyHandle": "2-in-1-phone-computer-screen-cleaner-kit-for-screen-dust-removal-microfiber-cloth-set-cjsj",
      "adminShopifyStatus": "ACTIVE",
      "generatedStorefrontUrl": "https://ivanreseller-2.myshopify.com/products/2-in-1-phone-computer-screen-cleaner-kit-for-screen-dust-removal-microfiber-cloth-set-cjsj",
      "storefront": {
        "status": 200,
        "finalUrl": "https://ivanreseller-2.myshopify.com/products/2-in-1-phone-computer-screen-cleaner-kit-for-screen-dust-removal-microfiber-cloth-set-cjsj",
        "buyerFacingOk": true,
        "passwordGate": false,
        "hasAddToCart": true,
        "hasPrice": true
      },
      "notes": []
    },
    {
      "listingId": 18,
      "productTitle": "Carbon Fiber Card Holder RFID Metal Wallet",
      "cjProductId": "1513778515970371584",
      "localStatusBefore": "ACTIVE",
      "classification": "ACTIVE_AND_STOREFRONT_OK",
      "shopifyProductId": "gid://shopify/Product/9146514473172",
      "shopifyVariantId": "gid://shopify/ProductVariant/47825654677716",
      "storedShopifyHandle": "rfid-carbon-fiber-card-holder-18",
      "adminShopifyHandle": "rfid-carbon-fiber-card-holder-18",
      "adminShopifyStatus": "ACTIVE",
      "generatedStorefrontUrl": "https://ivanreseller-2.myshopify.com/products/rfid-carbon-fiber-card-holder-18",
      "storefront": {
        "status": 200,
        "finalUrl": "https://ivanreseller-2.myshopify.com/products/rfid-carbon-fiber-card-holder-18",
        "buyerFacingOk": true,
        "passwordGate": false,
        "hasAddToCart": true,
        "hasPrice": true
      },
      "notes": []
    },
    {
      "listingId": 19,
      "productTitle": "RFID ID Bank Card Holder PU Mini Metal Wallet",
      "cjProductId": "1529035974012055552",
      "localStatusBefore": "DRAFT",
      "classification": "DRAFT",
      "shopifyProductId": null,
      "shopifyVariantId": null,
      "storedShopifyHandle": null,
      "adminShopifyHandle": null,
      "adminShopifyStatus": null,
      "generatedStorefrontUrl": null,
      "storefront": null,
      "notes": []
    },
    {
      "listingId": 20,
      "productTitle": "Stand Nordic Wrought Iron Mobile Phone Tablet Desktop Reading Organizer Storage Rack Decorative Desk Accessories",
      "cjProductId": "1398841574569414656",
      "localStatusBefore": "DRAFT",
      "classification": "DRAFT",
      "shopifyProductId": null,
      "shopifyVariantId": null,
      "storedShopifyHandle": null,
      "adminShopifyHandle": null,
      "adminShopifyStatus": null,
      "generatedStorefrontUrl": null,
      "storefront": null,
      "notes": []
    },
    {
      "listingId": 21,
      "productTitle": "Creative Cute Lucky Elephant Eyeglass Stand Holder  Decorative Display Rack For Eyewear Shop, Home, And Office Desk Organizer",
      "cjProductId": "2006273772812259330",
      "localStatusBefore": "DRAFT",
      "classification": "DRAFT",
      "shopifyProductId": null,
      "shopifyVariantId": null,
      "storedShopifyHandle": null,
      "adminShopifyHandle": null,
      "adminShopifyStatus": null,
      "generatedStorefrontUrl": null,
      "storefront": null,
      "notes": []
    },
    {
      "listingId": 22,
      "productTitle": "Multi-purpose Bank Card Holder Metal Wallet Carbon Fiber RFID Card Holder",
      "cjProductId": "1364534602391228416",
      "localStatusBefore": "DRAFT",
      "classification": "DRAFT",
      "shopifyProductId": null,
      "shopifyVariantId": null,
      "storedShopifyHandle": null,
      "adminShopifyHandle": null,
      "adminShopifyStatus": null,
      "generatedStorefrontUrl": null,
      "storefront": null,
      "notes": []
    },
    {
      "listingId": 23,
      "productTitle": "Monitor Stand Riser 3 Height Adjustable Desk Riser Organizer With Ventilation Holes",
      "cjProductId": "1990623364367704065",
      "localStatusBefore": "DRAFT",
      "classification": "DRAFT",
      "shopifyProductId": null,
      "shopifyVariantId": null,
      "storedShopifyHandle": null,
      "adminShopifyHandle": null,
      "adminShopifyStatus": null,
      "generatedStorefrontUrl": null,
      "storefront": null,
      "notes": []
    },
    {
      "listingId": 24,
      "productTitle": "Business Travel Organizer",
      "cjProductId": "0258D218-2849-4BED-B9F9-5F3BF9F7311D",
      "localStatusBefore": "DRAFT",
      "classification": "DRAFT",
      "shopifyProductId": null,
      "shopifyVariantId": null,
      "storedShopifyHandle": null,
      "adminShopifyHandle": null,
      "adminShopifyStatus": null,
      "generatedStorefrontUrl": null,
      "storefront": null,
      "notes": []
    },
    {
      "listingId": 25,
      "productTitle": "Electronics Organizer Travel Cable Organizer Bag Waterproof Portable Digital Storage Bag Electronic Accessories Case Cable Charger Organizer Case",
      "cjProductId": "1703055389602238464",
      "localStatusBefore": "DRAFT",
      "classification": "DRAFT",
      "shopifyProductId": null,
      "shopifyVariantId": null,
      "storedShopifyHandle": null,
      "adminShopifyHandle": null,
      "adminShopifyStatus": null,
      "generatedStorefrontUrl": null,
      "storefront": null,
      "notes": []
    },
    {
      "listingId": 26,
      "productTitle": "6 PCS Travel Storage Bag Set for Clothes Tidy Organizer",
      "cjProductId": "1384767271133646848",
      "localStatusBefore": "ACTIVE",
      "classification": "ACTIVE_AND_STOREFRONT_OK",
      "shopifyProductId": "gid://shopify/Product/9146510278868",
      "shopifyVariantId": "gid://shopify/ProductVariant/47825650385108",
      "storedShopifyHandle": "6-piece-travel-storage-bag-set-26",
      "adminShopifyHandle": "6-piece-travel-storage-bag-set-26",
      "adminShopifyStatus": "ACTIVE",
      "generatedStorefrontUrl": "https://ivanreseller-2.myshopify.com/products/6-piece-travel-storage-bag-set-26",
      "storefront": {
        "status": 200,
        "finalUrl": "https://ivanreseller-2.myshopify.com/products/6-piece-travel-storage-bag-set-26",
        "buyerFacingOk": true,
        "passwordGate": false,
        "hasAddToCart": true,
        "hasPrice": true
      },
      "notes": []
    },
    {
      "listingId": 27,
      "productTitle": "Travel Cosmetic & Toiletry Organizer Bag",
      "cjProductId": "7670B4F6-862B-4F2E-B78C-6B7337DC494F",
      "localStatusBefore": "ACTIVE",
      "classification": "ACTIVE_AND_STOREFRONT_OK",
      "shopifyProductId": "gid://shopify/Product/9146511556820",
      "shopifyVariantId": "gid://shopify/ProductVariant/47825651761364",
      "storedShopifyHandle": "travel-toiletry-organizer-bag-27",
      "adminShopifyHandle": "travel-toiletry-organizer-bag-27",
      "adminShopifyStatus": "ACTIVE",
      "generatedStorefrontUrl": "https://ivanreseller-2.myshopify.com/products/travel-toiletry-organizer-bag-27",
      "storefront": {
        "status": 200,
        "finalUrl": "https://ivanreseller-2.myshopify.com/products/travel-toiletry-organizer-bag-27",
        "buyerFacingOk": true,
        "passwordGate": false,
        "hasAddToCart": true,
        "hasPrice": true
      },
      "notes": []
    },
    {
      "listingId": 28,
      "productTitle": "Wire Cable Organizer Clips Self-Adhesive",
      "cjProductId": "876DB4DF-2542-4D3C-AA85-CEBFD8237DD8",
      "localStatusBefore": "ACTIVE",
      "classification": "ACTIVE_AND_STOREFRONT_OK",
      "shopifyProductId": "gid://shopify/Product/9146512376020",
      "shopifyVariantId": "gid://shopify/ProductVariant/47825652580564",
      "storedShopifyHandle": "self-adhesive-cable-organizer-clips-28",
      "adminShopifyHandle": "self-adhesive-cable-organizer-clips-28",
      "adminShopifyStatus": "ACTIVE",
      "generatedStorefrontUrl": "https://ivanreseller-2.myshopify.com/products/self-adhesive-cable-organizer-clips-28",
      "storefront": {
        "status": 200,
        "finalUrl": "https://ivanreseller-2.myshopify.com/products/self-adhesive-cable-organizer-clips-28",
        "buyerFacingOk": true,
        "passwordGate": false,
        "hasAddToCart": true,
        "hasPrice": true
      },
      "notes": []
    },
    {
      "listingId": 29,
      "productTitle": "Folding Aluminum Alloy Tablet Phone Lazy Stand",
      "cjProductId": "1375003219515805696",
      "localStatusBefore": "ACTIVE",
      "classification": "ACTIVE_AND_STOREFRONT_OK",
      "shopifyProductId": "gid://shopify/Product/9146513162452",
      "shopifyVariantId": "gid://shopify/ProductVariant/47825653334228",
      "storedShopifyHandle": "foldable-aluminum-tablet-stand-29",
      "adminShopifyHandle": "foldable-aluminum-tablet-stand-29",
      "adminShopifyStatus": "ACTIVE",
      "generatedStorefrontUrl": "https://ivanreseller-2.myshopify.com/products/foldable-aluminum-tablet-stand-29",
      "storefront": {
        "status": 200,
        "finalUrl": "https://ivanreseller-2.myshopify.com/products/foldable-aluminum-tablet-stand-29",
        "buyerFacingOk": true,
        "passwordGate": false,
        "hasAddToCart": true,
        "hasPrice": true
      },
      "notes": []
    },
    {
      "listingId": 30,
      "productTitle": "Keyboard wrist rest and mouse wrist rest",
      "cjProductId": "CD6A14B6-2DC9-400F-9BD0-B6AFF13B31A0",
      "localStatusBefore": "ACTIVE",
      "classification": "ACTIVE_AND_STOREFRONT_OK",
      "shopifyProductId": "gid://shopify/Product/9146513817812",
      "shopifyVariantId": "gid://shopify/ProductVariant/47825654087892",
      "storedShopifyHandle": "keyboard-and-mouse-wrist-rest-set-30",
      "adminShopifyHandle": "keyboard-and-mouse-wrist-rest-set-30",
      "adminShopifyStatus": "ACTIVE",
      "generatedStorefrontUrl": "https://ivanreseller-2.myshopify.com/products/keyboard-and-mouse-wrist-rest-set-30",
      "storefront": {
        "status": 200,
        "finalUrl": "https://ivanreseller-2.myshopify.com/products/keyboard-and-mouse-wrist-rest-set-30",
        "buyerFacingOk": true,
        "passwordGate": false,
        "hasAddToCart": true,
        "hasPrice": true
      },
      "notes": []
    },
    {
      "listingId": 31,
      "productTitle": "Car Seat Gap Filler Organizer Car Seat Console Organizer For Keys Phones And Sunglasses",
      "cjProductId": "1803978693954916352",
      "localStatusBefore": "ACTIVE",
      "classification": "ACTIVE_AND_STOREFRONT_OK",
      "shopifyProductId": "gid://shopify/Product/9146515226836",
      "shopifyVariantId": "gid://shopify/ProductVariant/47825655431380",
      "storedShopifyHandle": "car-seat-gap-organizer-31",
      "adminShopifyHandle": "car-seat-gap-organizer-31",
      "adminShopifyStatus": "ACTIVE",
      "generatedStorefrontUrl": "https://ivanreseller-2.myshopify.com/products/car-seat-gap-organizer-31",
      "storefront": {
        "status": 200,
        "finalUrl": "https://ivanreseller-2.myshopify.com/products/car-seat-gap-organizer-31",
        "buyerFacingOk": true,
        "passwordGate": false,
        "hasAddToCart": true,
        "hasPrice": true
      },
      "notes": []
    },
    {
      "listingId": 32,
      "productTitle": "Lipstick Organizer,Small Clear Plastic Compact Lip Gloss Chapstick Perfume Sample Mascara Holder With 9,24,36,40 Slots",
      "cjProductId": "1937397252993245185",
      "localStatusBefore": "DRAFT",
      "classification": "DRAFT",
      "shopifyProductId": "gid://shopify/Product/9146516046036",
      "shopifyVariantId": "gid://shopify/ProductVariant/47825656545492",
      "storedShopifyHandle": "lipstick-organizer-small-clear-plastic-compact-lip-gloss-chapstick-perfume-sample-mascara",
      "adminShopifyHandle": null,
      "adminShopifyStatus": null,
      "generatedStorefrontUrl": null,
      "storefront": null,
      "notes": []
    },
    {
      "listingId": 33,
      "productTitle": "Kitchen Silent Rotary Adjustable Digital Timer",
      "cjProductId": "1623483773528584192",
      "localStatusBefore": "ACTIVE",
      "classification": "ACTIVE_AND_STOREFRONT_OK",
      "shopifyProductId": "gid://shopify/Product/9146520862932",
      "shopifyVariantId": "gid://shopify/ProductVariant/47825662836948",
      "storedShopifyHandle": "rotary-digital-kitchen-timer-33",
      "adminShopifyHandle": "rotary-digital-kitchen-timer-33",
      "adminShopifyStatus": "ACTIVE",
      "generatedStorefrontUrl": "https://ivanreseller-2.myshopify.com/products/rotary-digital-kitchen-timer-33",
      "storefront": {
        "status": 200,
        "finalUrl": "https://ivanreseller-2.myshopify.com/products/rotary-digital-kitchen-timer-33",
        "buyerFacingOk": true,
        "passwordGate": false,
        "hasAddToCart": true,
        "hasPrice": true
      },
      "notes": []
    }
  ]
}
